cythereal_neomodel-3.3.5.data/scripts/neomodel_install_labels
cythereal_neomodel-3.3.5.data/scripts/neomodel_remove_labels
neomodel/__init__.py
neomodel/cardinality.py
neomodel/config.py
neomodel/core.py
neomodel/exception.py
neomodel/exceptions.py
neomodel/hooks.py
neomodel/match.py
neomodel/match_q.py
neomodel/properties.py
neomodel/relationship.py
neomodel/relationship_manager.py
neomodel/util.py
neomodel/contrib/__init__.py
neomodel/contrib/semi_structured.py
neomodel/contrib/spatial_properties.py
cythereal_neomodel-3.3.5.dist-info/AUTHORS.txt
cythereal_neomodel-3.3.5.dist-info/LICENSE
cythereal_neomodel-3.3.5.dist-info/METADATA
cythereal_neomodel-3.3.5.dist-info/WHEEL
cythereal_neomodel-3.3.5.dist-info/top_level.txt
cythereal_neomodel-3.3.5.dist-info/zip-safe
cythereal_neomodel-3.3.5.dist-info/RECORD
