Metadata-Version: 2.1
Name: cythereal-neomodel
Version: 3.3.5
Summary: An object mapper for the neo4j graph database.
Home-page: http://github.com/neo4j-contrib/neomodel
Author: Robin Edwards
Author-email: robin.ge@gmail.com
License: MIT
Keywords: graph neo4j ORM OGM
Platform: UNKNOWN
Classifier: Development Status :: 5 - Production/Stable
Classifier: Intended Audience :: Developers
Classifier: Operating System :: OS Independent
Classifier: License :: OSI Approved :: MIT License
Classifier: Programming Language :: Python
Classifier: Topic :: Software Development :: Libraries :: Python Modules
Classifier: Programming Language :: Python :: 2.7
Classifier: Programming Language :: Python :: 3.4
Classifier: Programming Language :: Python :: 3.5
Classifier: Programming Language :: Python :: 3.6
Classifier: Topic :: Database
License-File: LICENSE
License-File: AUTHORS.txt
Requires-Dist: neo4j-driver (==1.7.2)
Requires-Dist: pytz (>=2016.10)
